server/__init__.py
server/app.py
server/lib/__init__.py
server/lib/api/__init__.py
server/lib/api/inference.py
server/lib/api/provider.py
server/lib/api/response_utils.py
server/lib/entities.py
server/lib/event_emitter.py
server/lib/inference/__init__.py
server/lib/inference/huggingface/__init__.py
server/lib/inference/huggingface/generator.py
server/lib/inference/huggingface/helpers.py
server/lib/inference/huggingface/hf.py
server/lib/sse.py
server/lib/sseserver.py
server/lib/storage.py
server/models.json
server/requirements.txt
server/static/index.d826928d.js
server/static/index.d826928d.js.br
server/static/index.d826928d.js.gz
server/static/index.e96bf64d.css
server/static/index.e96bf64d.css.br
server/static/index.e96bf64d.css.gz
server/static/index.html
server/static/index.html.br
server/static/index.html.gz
openplayground-0.1.5.dist-info/LICENSE
openplayground-0.1.5.dist-info/METADATA
openplayground-0.1.5.dist-info/WHEEL
openplayground-0.1.5.dist-info/entry_points.txt
openplayground-0.1.5.dist-info/RECORD
