Metadata-Version: 2.1
Name: openplayground
Version: 0.1.5
Summary: An LLM playground you can run on your laptop.
Home-page: https://nat.dev/
Keywords: llm,playground,openplayground
Author: Nat Friedman
Author-email: nat@nat.org
Requires-Python: >=3.9,<4.0
Classifier: Programming Language :: Python :: 3
Classifier: Programming Language :: Python :: 3.9
Classifier: Programming Language :: Python :: 3.10
Classifier: Programming Language :: Python :: 3.11
Requires-Dist: Flask (>=2.2.3,<3.0.0)
Requires-Dist: Flask_Cors (>=3.0.10,<4.0.0)
Requires-Dist: aleph_alpha_client (>=2.16.1,<3.0.0)
Requires-Dist: anthropic (>=0.2.3,<0.3.0)
Requires-Dist: cachetools (>=5.3.0,<6.0.0)
Requires-Dist: click (>=8.1.3,<9.0.0)
Requires-Dist: huggingface_hub (>=0.13.2,<0.14.0)
Requires-Dist: openai (>=0.27.2,<0.28.0)
Requires-Dist: psutil (>=5.9.4,<6.0.0)
Requires-Dist: python-dotenv (>=1.0.0,<2.0.0)
Requires-Dist: requests (>=2.28.2,<3.0.0)
Requires-Dist: six (>=1.16.0,<2.0.0)
Requires-Dist: sseclient (>=0.0.27,<0.0.28)
Requires-Dist: torch (>=2.0.0,<3.0.0)
Requires-Dist: transformers (>=4.27.1,<5.0.0)
Project-URL: Repository, https://github.com/nat/openplayground
